MANIFEST.in
README.md
setup.cfg
setup.py
RSSIngest/__init__.py
RSSIngest/definitions.py
RSSIngest.egg-info/PKG-INFO
RSSIngest.egg-info/SOURCES.txt
RSSIngest.egg-info/dependency_links.txt
RSSIngest.egg-info/requires.txt
RSSIngest.egg-info/top_level.txt
RSSIngest/bin/__init__.py
RSSIngest/bin/rss_ingest
RSSIngest/config/__init__.py
RSSIngest/config/config.yaml
RSSIngest/scripts/__init__.py
RSSIngest/scripts/article_interpreter.py
RSSIngest/scripts/local_runner.py
RSSIngest/scripts/rss_ingest.py
test/test_connection.py