Metadata-Version: 1.0
Name: RSSIngest
Version: 0.0.36
Summary: Module for ingesting news articles from various sources' RSS feeds.
Home-page: UNKNOWN
Author: Ash Prince
Author-email: i7629228@bournemouth.ac.uk
License: UNKNOWN
Platform: UNKNOWN
